itk/CleaverPython.py
itk/_CleaverPython.pyd
itk/__init_cleaver__.py
itk/itkCleaverImageToMeshFilterPython.py
itk/Configuration/CleaverConfig.py
itk/Configuration/Cleaver_snake_case.py
itk_cleaver.libs/msvcp140.dll
itk_cleaver.libs/tbb12.dll
itk_cleaver-1.3.1.dist-info/DELVEWHEEL
itk_cleaver-1.3.1.dist-info/LICENSE
itk_cleaver-1.3.1.dist-info/METADATA
itk_cleaver-1.3.1.dist-info/WHEEL
itk_cleaver-1.3.1.dist-info/top_level.txt
itk_cleaver-1.3.1.dist-info/RECORD
